boring_semantic_layer/__init__.py
boring_semantic_layer/api.py
boring_semantic_layer/compile_all.py
boring_semantic_layer/config.py
boring_semantic_layer/convert.py
boring_semantic_layer/expr.py
boring_semantic_layer/format.py
boring_semantic_layer/graph_utils.py
boring_semantic_layer/measure_scope.py
boring_semantic_layer/nested_access.py
boring_semantic_layer/ops.py
boring_semantic_layer/profile.py
boring_semantic_layer/projection_utils.py
boring_semantic_layer/query.py
boring_semantic_layer/utils.py
boring_semantic_layer/xorq_convert.py
boring_semantic_layer/yaml.py
boring_semantic_layer/agents/cli.py
boring_semantic_layer/agents/tools.py
boring_semantic_layer/agents/backends/__init__.py
boring_semantic_layer/agents/backends/langgraph.py
boring_semantic_layer/agents/backends/mcp.py
boring_semantic_layer/agents/chats/cli.py
boring_semantic_layer/agents/chats/slack.py
boring_semantic_layer/agents/eval/__init__.py
boring_semantic_layer/agents/eval/eval.py
boring_semantic_layer/agents/eval/questions.yaml
boring_semantic_layer/agents/tests/__init__.py
boring_semantic_layer/agents/tests/test_chart_handler.py
boring_semantic_layer/agents/tests/test_chats_cli.py
boring_semantic_layer/agents/tests/test_cli_skill.py
boring_semantic_layer/agents/tests/test_langgraph_backend.py
boring_semantic_layer/agents/tests/test_mcp_json_parsing.py
boring_semantic_layer/agents/tests/test_prompts.py
boring_semantic_layer/agents/tests/test_semantic_mcp.py
boring_semantic_layer/agents/tests/test_tools.py
boring_semantic_layer/agents/utils/chart_handler.py
boring_semantic_layer/agents/utils/prompts.py
boring_semantic_layer/agents/utils/tokens.py
boring_semantic_layer/chart/__init__.py
boring_semantic_layer/chart/altair_chart.py
boring_semantic_layer/chart/base.py
boring_semantic_layer/chart/plotext_chart.py
boring_semantic_layer/chart/plotly_chart.py
boring_semantic_layer/chart/utils.py
boring_semantic_layer/chart/md_parser/__init__.py
boring_semantic_layer/chart/md_parser/converter.py
boring_semantic_layer-0.3.3.dist-info/METADATA
boring_semantic_layer-0.3.3.dist-info/WHEEL
boring_semantic_layer-0.3.3.dist-info/entry_points.txt
boring_semantic_layer-0.3.3.dist-info/licenses/LICENSE
boring_semantic_layer-0.3.3.dist-info/RECORD
